kozmoai_platform_api/__init__.py
kozmoai_platform_api/assets/default_templates.json
kozmoai_platform_api/main.py
kozmoai_platform_api/response_models.py
kozmoai_platform_api/utils/__init__.py
kozmoai_platform_api/utils/api.py
kozmoai_platform_api/utils/openapi.py
kozmoai_platform_api/utils/widgets.py
kozmoai_platform_api-1.1.4.dev202506081902.dist-info/METADATA
kozmoai_platform_api-1.1.4.dev202506081902.dist-info/WHEEL
kozmoai_platform_api-1.1.4.dev202506081902.dist-info/entry_points.txt
kozmoai_platform_api-1.1.4.dev202506081902.dist-info/RECORD
