Metadata-Version: 2.3
Name: kozmoai-platform-api
Version: 1.1.4.dev202506081902
Summary: KozmoAI Platform API: Launch script and widgets builder for the KozmoAI Platform API and Workspace Backend Connector.
License: AGPL-3.0-only
Author: KozmoAI
Author-email: hello@kozmoai.co
Requires-Python: >=3.9,<3.13
Classifier: License :: OSI Approved :: GNU Affero General Public License v3
Classifier: Programming Language :: Python :: 3
Classifier: Programming Language :: Python :: 3.9
Classifier: Programming Language :: Python :: 3.10
Classifier: Programming Language :: Python :: 3.11
Classifier: Programming Language :: Python :: 3.12
Requires-Dist: deepdiff
Requires-Dist: kozmoai-core (>=1.4.0,<2.0.0)
Project-URL: Documentation, https://docs.kozmoai.co
Project-URL: Homepage, https://kozmoai.co
Project-URL: Repository, https://github.com/digitranslab/kozmoai-finance
